aider/__init__.py
aider/__main__.py
aider/args.py
aider/args_formatter.py
aider/commands.py
aider/diffs.py
aider/dump.py
aider/gui.py
aider/help.py
aider/help_pats.py
aider/history.py
aider/io.py
aider/linter.py
aider/llm.py
aider/main.py
aider/mdstream.py
aider/models.py
aider/prompts.py
aider/repo.py
aider/repomap.py
aider/scrape.py
aider/sendchat.py
aider/urls.py
aider/utils.py
aider/versioncheck.py
aider/voice.py
aider/coders/__init__.py
aider/coders/base_coder.py
aider/coders/base_prompts.py
aider/coders/editblock_coder.py
aider/coders/editblock_fenced_coder.py
aider/coders/editblock_fenced_prompts.py
aider/coders/editblock_func_coder.py
aider/coders/editblock_func_prompts.py
aider/coders/editblock_prompts.py
aider/coders/help_coder.py
aider/coders/help_prompts.py
aider/coders/search_replace.py
aider/coders/single_wholefile_func_coder.py
aider/coders/single_wholefile_func_prompts.py
aider/coders/udiff_coder.py
aider/coders/udiff_prompts.py
aider/coders/wholefile_coder.py
aider/coders/wholefile_func_coder.py
aider/coders/wholefile_func_prompts.py
aider/coders/wholefile_prompts.py
aider/queries/tree-sitter-c-tags.scm
aider/queries/tree-sitter-c_sharp-tags.scm
aider/queries/tree-sitter-cpp-tags.scm
aider/queries/tree-sitter-elisp-tags.scm
aider/queries/tree-sitter-elixir-tags.scm
aider/queries/tree-sitter-elm-tags.scm
aider/queries/tree-sitter-go-tags.scm
aider/queries/tree-sitter-java-tags.scm
aider/queries/tree-sitter-javascript-tags.scm
aider/queries/tree-sitter-ocaml-tags.scm
aider/queries/tree-sitter-php-tags.scm
aider/queries/tree-sitter-python-tags.scm
aider/queries/tree-sitter-ql-tags.scm
aider/queries/tree-sitter-ruby-tags.scm
aider/queries/tree-sitter-rust-tags.scm
aider/queries/tree-sitter-typescript-tags.scm
aider/tests/__init__.py
aider/tests/test_coder.py
aider/tests/test_commands.py
aider/tests/test_editblock.py
aider/tests/test_help.py
aider/tests/test_io.py
aider/tests/test_main.py
aider/tests/test_models.py
aider/tests/test_repo.py
test444888-1.0.dist-info/LICENSE.txt
test444888-1.0.dist-info/METADATA
test444888-1.0.dist-info/WHEEL
test444888-1.0.dist-info/entry_points.txt
test444888-1.0.dist-info/top_level.txt
test444888-1.0.dist-info/RECORD
